Metadata-Version: 2.1
Name: checksignature
Version: 0.1.1
Summary: a function decorator for enforcing function signatures
Home-page: https://github.com/withtwoemms/checksignature
Author: Emmanuel I. Obi
Maintainer: Emmanuel I. Obi
Maintainer-email: withtwoemms@gmail.com
License: MIT
Classifier: Development Status :: 3 - Alpha
Classifier: Intended Audience :: Developers
Classifier: Topic :: Software Development :: Build Tools
Classifier: License :: OSI Approved :: MIT License
Classifier: Programming Language :: Python :: 3.7
Classifier: Programming Language :: Python :: 3.8
Classifier: Programming Language :: Python :: 3.9
Classifier: Programming Language :: Python :: 3.10
Classifier: Programming Language :: Python :: 3.11
Classifier: Programming Language :: Python :: 3.12
License-File: LICENSE
